country_capitals/__init__.py
country_capitals/capitals.json
country_capitals/main.py
country_capitals-1.0.1.dist-info/METADATA
country_capitals-1.0.1.dist-info/WHEEL
country_capitals-1.0.1.dist-info/licenses/LICENSE
country_capitals-1.0.1.dist-info/RECORD
