Metadata-Version: 2.4
Name: country_capitals
Version: 1.0.1
Summary: Get the name of a country's capital city.
Project-URL: Homepage, https://github.com/KosayJabre/Country-Capitals
Author-email: Kosay Jabre <kosay.jabre@gmail.com>
License: This is free and unencumbered software released into the public domain.
License-File: LICENSE
Keywords: ISO 3166,ISO 3166-1,capitals,countries
Requires-Python: >=3.7
Requires-Dist: pycountry
